kotoha/__init__.py
kotoha/__main__.py
kotoha/core.py
kotoha/plugins.py
flake8_kotoha-0.1.0.dist-info/LICENSE
flake8_kotoha-0.1.0.dist-info/METADATA
flake8_kotoha-0.1.0.dist-info/WHEEL
flake8_kotoha-0.1.0.dist-info/entry_points.txt
flake8_kotoha-0.1.0.dist-info/top_level.txt
flake8_kotoha-0.1.0.dist-info/RECORD
