Metadata-Version: 2.1
Name: flake8-kotoha
Version: 0.1.0
Summary: flake8 plugin to improve your type hints
Author-email: nikkie <takuyafjp+develop@gmail.com>
License: MIT License
Project-URL: Repository, https://github.com/ftnext/kotoha-python-linter
Keywords: flake8,type hints
Classifier: License :: OSI Approved :: MIT License
Classifier: Programming Language :: Python
Classifier: Programming Language :: Python :: 3
Classifier: Programming Language :: Python :: 3 :: Only
Classifier: Programming Language :: Python :: 3.9
Classifier: Programming Language :: Python :: 3.10
Classifier: Programming Language :: Python :: 3.11
Classifier: Programming Language :: Python :: 3.12
Classifier: Framework :: Flake8
Classifier: Topic :: Software Development :: Libraries :: Python Modules
Classifier: Topic :: Software Development :: Quality Assurance
Requires-Python: >=3.9
License-File: LICENSE
Requires-Dist: flake8
Provides-Extra: dev
Requires-Dist: taskipy ; extra == 'dev'
Requires-Dist: autoflake ; extra == 'dev'
Requires-Dist: pyupgrade ; extra == 'dev'
Requires-Dist: black ; extra == 'dev'
Requires-Dist: isort ; extra == 'dev'
Requires-Dist: pytest ; extra == 'dev'
Requires-Dist: pytest-randomly ; extra == 'dev'
Requires-Dist: mypy ; extra == 'dev'
